<?xml version="1.0" encoding="UTF-8"?>
<Level>
	<caract tiempo="120" puntos="7000" vidas="1" health="300" spawnMin="1" spawnMax="1.5" />
	
	<arrow type="normal" prob="30" vel="2"/>
	<arrow type="fire" prob="20" vel="2"/>
	<arrow type="ice" prob="20" vel="2"/>
	<arrow type="plant" prob="10" vel="2"/>
	<arrow type="fast" prob="10" vel="3.5"/>
	<arrow type="elec" prob="10" vel="2"/>
	
	<panel type="fog">
		<status>false</status>
	</panel>
	
	<soldier x="20" y="265" arm="3" platf="300" />
	<soldier x="10" y="435" arm="2" platf="300" />
</Level>